quantiphy_eval.py
quantiphy_eval-0.5.0.dist-info/LICENSE
quantiphy_eval-0.5.0.dist-info/WHEEL
quantiphy_eval-0.5.0.dist-info/METADATA
quantiphy_eval-0.5.0.dist-info/RECORD
