Metadata-Version: 2.1
Name: quantiphy_eval
Version: 0.5.0
Summary: calculations with physical quantities
Keywords: quantities,physical,quantity,units,SI,scale factors,engineering,notation,mks,cgs
Author: Ken Kundert
Author-email: quantiphy@nurdletech.com
Maintainer: Ken Kundert
Maintainer-email: quantiphy@nurdletech.com
Requires-Python: >=3.6
Classifier: Development Status :: 4 - Beta
Classifier: Intended Audience :: Developers
Classifier: Intended Audience :: Science/Research
Classifier: License :: OSI Approved :: MIT License
Classifier: Natural Language :: English
Classifier: Operating System :: POSIX :: Linux
Classifier: Programming Language :: Python :: 3.6
Classifier: Programming Language :: Python :: 3.7
Classifier: Programming Language :: Python :: 3.8
Classifier: Programming Language :: Python :: 3.9
Classifier: Programming Language :: Python :: 3.10
Classifier: Topic :: Utilities
Classifier: Topic :: Scientific/Engineering
Requires-Dist: inform>=1.23
Requires-Dist: quantiphy>=2.13
Requires-Dist: sly>=0.4
Requires-Dist: pytest ; extra == "test"
Requires-Dist: pytest-cov ; extra == "test"
Requires-Dist: tox ; extra == "test"
Requires-Dist: pylama ; extra == "test"
Project-URL: changelog, https://github.com/kenkundert/quantiphy_eval#releases
Project-URL: documentation, https://github.com/kenkundert/quantiphy_eval
Project-URL: homepage, https://github.com/kenkundert/quantiphy_eval
Project-URL: repository, https://github.com/kenkundert/quantiphy_eval
Provides-Extra: test
